django_vite_boilerplate/__init__.py
django_vite_boilerplate/apps.py
django_vite_boilerplate/frontend_template/.cookiecutterignore
django_vite_boilerplate/frontend_template/cookiecutter.json
django_vite_boilerplate/frontend_template/hooks/post_gen_project.py
django_vite_boilerplate/frontend_template/{{cookiecutter.project_slug}}/.nvmrc
django_vite_boilerplate/frontend_template/{{cookiecutter.project_slug}}/application/app.css
django_vite_boilerplate/frontend_template/{{cookiecutter.project_slug}}/application/app.js
django_vite_boilerplate/frontend_template/{{cookiecutter.project_slug}}/application/app.scss
django_vite_boilerplate/frontend_template/{{cookiecutter.project_slug}}/package.json
django_vite_boilerplate/frontend_template/{{cookiecutter.project_slug}}/vite.config.js
django_vite_boilerplate/frontend_template/{{cookiecutter.project_slug}}/vite_django_config.json
django_vite_boilerplate/management/__init__.py
django_vite_boilerplate/management/commands/__init__.py
django_vite_boilerplate/management/commands/vite_init.py
django_vite_boilerplate-0.1.3.dist-info/METADATA
django_vite_boilerplate-0.1.3.dist-info/WHEEL
django_vite_boilerplate-0.1.3.dist-info/licenses/LICENSE
django_vite_boilerplate-0.1.3.dist-info/RECORD
